[
  {
    "title": "\u0986\u09ae\u09b0\u09be \u09b8\u0995\u09b2\u09c7 \u0987\u09a4\u09cb\u09ae\u09a7\u200d\u09cd\u09af\u09c7\u0987 \u099c\u09c7\u09a8\u09c7\u099b\u09bf Zero Olympiad \u098f\u09b0 \u09b8\u0995\u09b2 \u09aa\u09be\u09b0\u09cd\u099f\u09bf\u09b8\u09bf\u09aa\u09c7\u09a8\u09cd\u099f \u09b8\u09c1\u09af\u09cb\u0997 \u09aa\u09be\u09ac\u09c7 \u09ae\u09be\u09b2\u09df\u09c7\u09b6...",
    "description": "\u0986\u09ae\u09b0\u09be \u09b8\u0995\u09b2\u09c7 \u0987\u09a4\u09cb\u09ae\u09a7\u200d\u09cd\u09af\u09c7\u0987 \u099c\u09c7\u09a8\u09c7\u099b\u09bf Zero Olympiad \u098f\u09b0 \u09b8\u0995\u09b2 \u09aa\u09be\u09b0\u09cd\u099f\u09bf\u09b8\u09bf\u09aa\u09c7\u09a8\u09cd\u099f \u09b8\u09c1\u09af\u09cb\u0997 \u09aa\u09be\u09ac\u09c7 \u09ae\u09be\u09b2\u09df\u09c7\u09b6\u09bf\u09df\u09be\u09df Asia Pacific University \u09a4\u09c7 \u09e7\u09e6-\u09e7\u09e8 \u099c\u09c1\u09b2\u09be\u0987 \u09b8\u09b6\u09b0\u09c0\u09b0\u09c7 \u09af\u09cb\u0997 \u09a6\u09bf\u09df\u09c7 International Leadership Bootcamp \u098f \u0985\u0982\u09b6 \u09a8\u09c7\u09df\u09be\u09b0\u0964 \u098f\u09b0\u09aa\u09b0 \u0995\u09cb\u09a8 \u09a6\u09c7\u09b6? \u09b9\u09bf\u09a8\u09cd\u099f\u09b8 \u09b0\u09df\u09c7\u099b\u09c7 \u098f\u0987 \u099b\u09ac\u09bf\u09a4\u09c7\u0964 \u0989\u09a4\u09cd\u09a4\u09b0 \u099c\u09be\u09a8\u09be\u09a8 \u0995\u09ae\u09c7\u09a8\u09cd\u099f\u09c7\u0964",
    "link": "https://www.facebook.com/FaatihaAayatOfficial/posts/pfbid02ZxAZtVVWS3J26xHGQxBVeiLC174kAaeCf2NyHdHSXLEWRDSr2bUvPwujKvSvbjQwl",
    "guid": "https://www.facebook.com/FaatihaAayatOfficial/posts/pfbid02ZxAZtVVWS3J26xHGQxBVeiLC174kAaeCf2NyHdHSXLEWRDSr2bUvPwujKvSvbjQwl",
    "pubDate": "2026-04-21T07:07:26.705053+00:00",
    "image": "https://scontent-dfw6-1.xx.fbcdn.net/v/t39.30808-6/672685711_1982833135690425_2727600831855002097_n.jpg?stp=dst-jpg_p526x296_tt6&_nc_cat=1&ccb=1-7&_nc_sid=dd6889&_nc_ohc=VQngBA7Zi0IQ7kNvwFPqvck&_nc_oc=AdpQL4mS4oYTa2hBoH5sco8uHCdBrgSwji8iSx4fedLaouBx4UangsNn64xh9QhqASw&_nc_zt=23&_nc_ht=scontent-dfw6-1.xx&_nc_gid=haC5S1agmk8GlvtOuXMh6g&_nc_ss=7a389&oh=00_Af3oz1pzmpegcZi8YH0_Woqi6RVwKILd1nqjPBg-Tdifqg&oe=69ED2085"
  },
  {
    "title": "#AssalamuAlaikum to all participants, ambassadors, patrons, mentors and well wis...",
    "description": "#AssalamuAlaikum to all participants, ambassadors, patrons, mentors and well wishers of Zero Olympiad.",
    "link": "https://www.facebook.com/FaatihaAayatOfficial/posts/pfbid028foSyGfbDP3zQ4XEtMRAgqn1gQnDYNG3yc4dnQSfHpQgkTqXmF8qRDrAHfPA5ehyl",
    "guid": "https://www.facebook.com/FaatihaAayatOfficial/posts/pfbid028foSyGfbDP3zQ4XEtMRAgqn1gQnDYNG3yc4dnQSfHpQgkTqXmF8qRDrAHfPA5ehyl",
    "pubDate": "2026-04-21T05:07:28.756766+00:00",
    "image": "https://scontent-dfw6-1.xx.fbcdn.net/v/t39.30808-6/672683909_1982767865696952_7376235385695815661_n.jpg?stp=cp6_dst-jpg_tt6&_nc_cat=102&ccb=1-7&_nc_sid=dd6889&_nc_ohc=H_7mAm_fdFoQ7kNvwGHaRUY&_nc_oc=AdoBwiivlNbGaS6ktc02SYX3Hzh9q443OJCvmbIOMMDK21Cwj-oZxAyOw1LRJyR-C5M&_nc_zt=23&_nc_ht=scontent-dfw6-1.xx&_nc_gid=V-CMku7eXpns5XRYyeqamQ&_nc_ss=7a389&oh=00_Af0pFd05Bmac99D0eJY1QMjkUKl9ge5fj9DaQYKtU_h_xQ&oe=69ED3C3E"
  },
  {
    "title": "\u0986\u099c \u0986\u09ae\u09b0\u09be \u09aa\u09cd\u09b0\u09a4\u09bf\u09a6\u09bf\u09a8 social media-\u09a4\u09c7 \u0985\u09b8\u0982\u0996\u09cd\u09af \u09aa\u09cb\u09b8\u09cd\u099f \u09a6\u09c7\u0996\u09bf\u2014climate change, education cri...",
    "description": "\u0986\u099c \u0986\u09ae\u09b0\u09be \u09aa\u09cd\u09b0\u09a4\u09bf\u09a6\u09bf\u09a8 social media-\u09a4\u09c7 \u0985\u09b8\u0982\u0996\u09cd\u09af \u09aa\u09cb\u09b8\u09cd\u099f \u09a6\u09c7\u0996\u09bf\u2014climate change, education crisis, inequality\u2026 \u0995\u09bf\u09a8\u09cd\u09a4\u09c1 \u098f\u0995\u099f\u09be \u09aa\u09cd\u09b0\u09b6\u09cd\u09a8\u2014 \ufffd \u0986\u09ae\u09b0\u09be \u0995\u09bf \u09b6\u09c1\u09a7\u09c1 \u09a6\u09c7\u0996\u09c7\u0987 \u09a5\u09c7\u09ae\u09c7 \u09af\u09be\u099a\u09cd\u099b\u09bf? \u098f\u0987 \u09b2\u09be\u0987\u09ad\u09c7 \u0986\u09ae\u09b0\u09be \u0995\u09a5\u09be \u09ac\u09b2\u09ac\u09cb\u2014 \ufffd \u0995\u09c7\u09a8 \u09b6\u09c1\u09a7\u09c1 awareness \u09af\u09a5\u09c7\u09b7\u09cd\u099f \u09a8\u09be \ufffd \u0995\u09c0\u09ad\u09be\u09ac\u09c7 \u098f\u0995\u099c\u09a8 \u09a4\u09b0\u09c1\u09a3 real impact \u09a4\u09c8\u09b0\u09bf \u0995\u09b0\u09a4\u09c7 \u09aa\u09be\u09b0\u09c7 \ufffd Zero Olympiad \u0995\u09c0\u09ad\u09be\u09ac\u09c7 change-makers \u09a4\u09c8\u09b0\u09bf \u0995\u09b0\u099b\u09c7 \u098f\u0987 \u0986\u09b2\u09cb\u099a\u09a8\u09be \u09b6\u09c1\u09a7\u09c1 \u0995\u09a5\u09be \u09a8\u09be\u2014\u098f\u099f\u09be \u09b9\u09a4\u09c7 \u09aa\u09be\u09b0\u09c7 \u09a4\u09cb\u09ae\u09be\u09b0 life-\u098f\u09b0 turning point\u0964 Join now. Think. Question. Act.",
    "link": "https://www.facebook.com/FaatihaAayatOfficial/videos/2453855165051792/",
    "guid": "https://www.facebook.com/FaatihaAayatOfficial/videos/2453855165051792/",
    "pubDate": "2026-04-20T15:07:30.806498+00:00",
    "image": "https://scontent-dfw5-2.xx.fbcdn.net/v/t15.5256-10/676262146_961194362980620_1026208171697576944_n.jpg?stp=dst-jpg_s960x960_tt6&_nc_cat=108&ccb=1-7&_nc_sid=032300&_nc_ohc=4F3B5Ys1tbQQ7kNvwF0C0nR&_nc_oc=AdpMFpDny6G-wnswvg6RLyeYwOWM2hE3bKUeyR4O2L6vETCfXg46U6J5nA6ftMgfQhU&_nc_zt=23&_nc_ht=scontent-dfw5-2.xx&_nc_gid=V-CMku7eXpns5XRYyeqamQ&_nc_ss=7a389&oh=00_Af2ywEVJr6gUNIH4cxTCEB2pGSMoFiLSMVnitsaJY2g58A&oe=69ED272A"
  },
  {
    "title": "#CEO \u0995\u09bf\u09ad\u09be\u09ac\u09c7 \u09b9\u09ac? \u09aa\u09cd\u09b0\u09a5\u09ae\u09c7 Zero Olympiad \u098f\u09b0 \u0993\u09df\u09c7\u09ac\u09b8\u09be\u0987\u099f\u09c7 \u09b0\u09c7\u099c\u09bf\u09b8\u09cd\u099f\u09cd\u09b0\u09c7\u09b6\u09a8 \u0995\u09b0\u09a4\u09c7 \u09b9\u09ac\u09c7\u0964 \u098f\u09b0\u09aa\u09b0 \u0986\u09aa...",
    "description": "#CEO \u0995\u09bf\u09ad\u09be\u09ac\u09c7 \u09b9\u09ac? \u09aa\u09cd\u09b0\u09a5\u09ae\u09c7 Zero Olympiad \u098f\u09b0 \u0993\u09df\u09c7\u09ac\u09b8\u09be\u0987\u099f\u09c7 \u09b0\u09c7\u099c\u09bf\u09b8\u09cd\u099f\u09cd\u09b0\u09c7\u09b6\u09a8 \u0995\u09b0\u09a4\u09c7 \u09b9\u09ac\u09c7\u0964 \u098f\u09b0\u09aa\u09b0 \u0986\u09aa\u09a8\u09bf \u09b8\u09bf\u0987\u0993 \u09b9\u09df\u09c7 \u0995\u09be\u099c \u0995\u09b0\u09a4\u09c7 \u0986\u0997\u09cd\u09b0\u09b9\u09c0 \u09b9\u09b2\u09c7 \u0986\u09aa\u09a8\u09be\u09b0 \u0987\u09ae\u09c7\u0987\u09b2 \u0985\u09cd\u09af\u09be\u09a1\u09cd\u09b0\u09c7\u09b8 \u09e6\u09e7\u09ef\u09ed\u09e9\u09eb\u09ed\u09e6\u09e8\u09e6\u09e9 \u09a8\u09ae\u09cd\u09ac\u09b0\u09c7 \u09b9\u09cb\u09df\u09be\u099f\u09b8\u0985\u09cd\u09af\u09be\u09aa \u0995\u09b0\u09c7 \u09aa\u09be\u09a0\u09be\u09a8\u0964 \u0986\u09aa\u09a8\u09be\u0995\u09c7 \u0986\u09ae\u09be\u09a6\u09c7\u09b0 \u0993\u09df\u09c7\u09ac\u09b8\u09be\u0987\u099f\u09c7 \u0985\u09cd\u09af\u09be\u09ae\u09cd\u09ac\u09be\u09b8\u09c7\u09a1\u09b0 \u09aa\u09cd\u09af\u09be\u09a8\u09c7\u09b2\u09c7 \u0985\u09cd\u09af\u09be\u0995\u09b8\u09c7\u09b8 \u09a6\u09bf\u09df\u09be \u09b9\u09ac\u09c7\u0964 \u09a4\u09be\u09b0\u09aa\u09b0 \u0986\u09aa\u09a8\u09bf \u09b2\u0997 \u0986\u0989\u099f \u09b9\u09df\u09c7 \u0986\u09ac\u09be\u09b0 \u09b2\u0997 \u0987\u09a8 \u0995\u09b0\u09b2\u09c7 \u201cAmbassador Panel\u201d \u09a6\u09c7\u0996\u09a4\u09c7 \u09aa\u09be\u09ac\u09c7\u09a8\u0964 \u09b8\u09c7\u0996\u09be\u09a8 \u09a5\u09c7\u0995\u09c7 \u09a8\u09bf\u099c\u09c7\u09b0 \u0995\u09cb\u09a1 \u09a0\u09bf\u0995 \u0995\u09b0\u09c7 \u09a8\u09bf\u09ac\u09c7\u09a8\u0964 \u098f\u0987 \u0995\u09cb\u09a1 \u09ac\u09cd\u09af\u09ac\u09b9\u09be\u09b0 \u0995\u09b0\u09c7 \u0985\u09a8\u09cd\u09af\u09a6\u09c7\u09b0 \u09b0\u09c7\u099c\u09bf\u09b8\u09cd\u099f\u09cd\u09b0\u09c7\u09b6\u09a8 \u0995\u09b0\u09a4\u09c7 \u09ac\u09b2\u09c7\u09ac\u09a8\u0964 \u09a4\u09be\u09b9\u09b2\u09c7\u0987 \u0986\u09ae\u09b0\u09be \u09ac\u09c1\u099d\u09a4\u09c7 \u09aa\u09be\u09b0\u09ac \u0995\u09a4\u099c\u09a8 \u0986\u09aa\u09a8\u09be\u09b0 \u09ae\u09be\u09a7\u09cd\u09af\u09ae\u09c7 \u09b0\u09c7\u099c\u09bf\u09b8\u09cd\u099f\u09cd\u09b0\u09c7\u09b6\u09a8 \u0995\u09b0\u09b2\u0964 \u09ae\u09bf\u09a8\u09bf\u09ae\u09be\u09ae \u09eb \u099c\u09a8 \u0995\u09b0\u09b2\u09c7\u0987 \u0986\u09aa\u09a8\u09bf \u09aa\u09c7\u09df\u09c7 \u09af\u09be\u09ac\u09c7\u09a8 \u09b8\u09bf\u0987\u0993 \u09b9\u09bf\u09b8\u09c7\u09ac\u09c7 \u0985\u09ab\u09bf\u09b8\u09bf\u09df\u09be\u09b2 \u09b0\u09bf\u0995\u0997\u09a8\u09bf\u09b6\u09a8\u0964 \u09b8\u09bf\u0987\u0993 \u09b9\u09a4\u09c7 \u09aa\u09be\u09b0\u09b2\u09c7 \u09b2\u09be\u09ad \u0995\u09bf? \u0989\u09a4\u09cd\u09a4\u09b0 \u09a6\u09c7\u0996\u09c1\u09a8 \u0995\u09ae\u09c7\u09a8\u09cd\u099f\u09c7\u0964",
    "link": "https://www.facebook.com/FaatihaAayatOfficial/posts/pfbid02DSYGzqAVhcViaJGiBqtwCXDXCfjEbYf16a21KGagGSP1jNcqS7VrTs9puVYhrHWjl",
    "guid": "https://www.facebook.com/FaatihaAayatOfficial/posts/pfbid02DSYGzqAVhcViaJGiBqtwCXDXCfjEbYf16a21KGagGSP1jNcqS7VrTs9puVYhrHWjl",
    "pubDate": "2026-04-20T12:07:32.854659+00:00",
    "image": "https://scontent-dfw5-2.xx.fbcdn.net/v/t39.30808-6/675450099_1982138485759890_6738278982334626133_n.jpg?stp=dst-jpg_s960x960_tt6&_nc_cat=100&ccb=1-7&_nc_sid=13d280&_nc_ohc=WhnluybC7koQ7kNvwFf4dNZ&_nc_oc=AdoATC4OMfAkG_Fa6dnBa_mzUFLQU4H9W2ceYPqd9ajfa-iphvRwSYz6Yho50JG4kTY&_nc_zt=23&_nc_ht=scontent-dfw5-2.xx&_nc_gid=V-CMku7eXpns5XRYyeqamQ&_nc_ss=7a389&oh=00_Af037usR3D3l7Gc1reQxUJoWq57P7b2s-2BJDbqqIy62aQ&oe=69ED3273"
  },
  {
    "title": "\u09ac\u09c7\u09b0\u09bf\u09df\u09c7 \u098f\u09b8\u09cb\u0964 \u09a8\u09bf\u099c\u09c7\u09b0 \u09b8\u09c0\u09ae\u09be\u09b0\u09c7\u0996\u09be \u09ad\u09c7\u0999\u09c7, \u09a8\u09bf\u099c\u09c7\u09b0 \u09ad\u09c7\u09a4\u09b0\u09c7\u09b0 \u0985\u09a6\u09c7\u0996\u09be \u09b6\u0995\u09cd\u09a4\u09bf\u099f\u09be\u0995\u09c7 \u099c\u09be\u0997\u09bf\u09df\u09c7\u0964 \u0985\u09a8\u09c1\u09a7\u09be\u09ac\u09a8 \u0995\u09b0...",
    "description": "\u09ac\u09c7\u09b0\u09bf\u09df\u09c7 \u098f\u09b8\u09cb\u0964 \u09a8\u09bf\u099c\u09c7\u09b0 \u09b8\u09c0\u09ae\u09be\u09b0\u09c7\u0996\u09be \u09ad\u09c7\u0999\u09c7, \u09a8\u09bf\u099c\u09c7\u09b0 \u09ad\u09c7\u09a4\u09b0\u09c7\u09b0 \u0985\u09a6\u09c7\u0996\u09be \u09b6\u0995\u09cd\u09a4\u09bf\u099f\u09be\u0995\u09c7 \u099c\u09be\u0997\u09bf\u09df\u09c7\u0964 \u0985\u09a8\u09c1\u09a7\u09be\u09ac\u09a8 \u0995\u09b0\u09c7 \u09af\u09c7 \u09a4\u09c1\u09ae\u09bf \u09a8\u09bf\u099c\u09c7\u0987 \u09b8\u09ae\u09cd\u09ad\u09be\u09ac\u09a8\u09be\u09b0 \u098f\u0995 \u0985\u09a8\u09a8\u09cd\u09a4 \u09ae\u09b9\u09be\u0995\u09be\u09ac\u09cd\u09af\u0964 \u098f\u0995\u099f\u09be \u0995\u09a3\u09cd\u09a0, \u09af\u0996\u09a8 \u09b8\u09be\u09b9\u09b8 \u09aa\u09be\u09df \u09b8\u09c7\u099f\u09be \u0986\u09b0 \u09b6\u09c1\u09a7\u09c1 \u0995\u09a3\u09cd\u09a0 \u09a5\u09be\u0995\u09c7 \u09a8\u09be, \u09b9\u09df\u09c7 \u0993\u09a0\u09c7 \u0986\u09a8\u09cd\u09a6\u09cb\u09b2\u09a8\u0964 \u098f\u0995\u099f\u09be \u09aa\u09a6\u0995\u09cd\u09b7\u09c7\u09aa, \u09af\u0996\u09a8 \u09ac\u09bf\u09b6\u09cd\u09ac\u09be\u09b8\u09c7 \u09ad\u09b0\u09c7 \u0993\u09a0\u09c7 \u09b8\u09c7\u099f\u09be \u0986\u09b0 \u09b6\u09c1\u09a7\u09c1 \u09b9\u09be\u0981\u099f\u09be \u09a5\u09be\u0995\u09c7 \u09a8\u09be, \u09b9\u09df\u09c7 \u0993\u09a0\u09c7 \u0987\u09a4\u09bf\u09b9\u09be\u09b8\u09c7\u09b0 \u09b6\u09c1\u09b0\u09c1\u0964 Zero Olympiad \u09b8\u09c7\u0987 \u09a6\u09b0\u099c\u09be, \u09af\u09c7\u0996\u09be\u09a8\u09c7 \u09a4\u09cb\u09ae\u09be\u09b0 \u201c\u0986\u09ae\u09bf \u09aa\u09be\u09b0\u09bf \u09a4\u09cb?\u201d \u09ac\u09a6\u09b2\u09c7 \u09af\u09be\u09df \u201c\u0986\u09ae\u09bf \u09aa\u09be\u09b0\u09ac\u0987\u201d-\u09a4\u09c7\u0964 \u098f\u0996\u09be\u09a8\u09c7 \u09aa\u09cd\u09b0\u09a4\u09bf\u099f\u09bf \u09aa\u09cd\u09b0\u09b6\u09cd\u09a8 \u09a4\u09cb\u09ae\u09be\u0995\u09c7 \u099a\u09cd\u09af\u09be\u09b2\u09c7\u099e\u09cd\u099c \u0995\u09b0\u09c7, \u09aa\u09cd\u09b0\u09a4\u09bf\u099f\u09bf \u0989\u09a4\u09cd\u09a4\u09b0 \u09a4\u09cb\u09ae\u09be\u0995\u09c7 \u09a8\u09a4\u09c1\u09a8 \u0995\u09b0\u09c7 \u0997\u09dc\u09c7\u0964 \u098f\u099f\u09be \u09b6\u09c1\u09a7\u09c1 \u098f\u0995\u099f\u09be \u09aa\u09cd\u09b0\u09a4\u09bf\u09af\u09cb\u0997\u09bf\u09a4\u09be \u09a8\u09be\u0964 \u098f\u099f\u09be \u09a8\u09bf\u099c\u09c7\u0995\u09c7 \u0985\u09a4\u09bf\u0995\u09cd\u09b0\u09ae \u0995\u09b0\u09be\u09b0 \u098f\u0995 \u09af\u09be\u09a4\u09cd\u09b0\u09be, \u09af\u09c7\u0996\u09be\u09a8\u09c7 \u09a4\u09c1\u09ae\u09bf \u09b9\u09be\u09b0\u09be\u0993 \u09a8\u09be, \u09a4\u09c1\u09ae\u09bf \u09a4\u09c8\u09b0\u09bf \u09b9\u0993\u0964 \u09a4\u09c1\u09ae\u09bf \u0995\u09bf \u09aa\u09cd\u09b0\u09b8\u09cd\u09a4\u09c1\u09a4 \u09a8\u09bf\u099c\u09c7\u0995\u09c7 \u099b\u09be\u09aa\u09bf\u09df\u09c7 \u09af\u09c7\u09a4\u09c7? \u09a4\u09c1\u09ae\u09bf \u0995\u09bf \u09aa\u09cd\u09b0\u09b8\u09cd\u09a4\u09c1\u09a4 \u09b8\u09c7\u0987 \u09b8\u0982\u09b8\u09cd\u0995\u09b0\u09a3\u099f\u09be\u0995\u09c7 \u099c\u09be\u0997\u09be\u09a4\u09c7, \u09af\u09be\u0995\u09c7 \u098f\u0996\u09a8\u09cb \u0995\u09c7\u0989 \u09a6\u09c7\u0996\u09c7\u09a8\u09bf? \u09a4\u09c1\u09ae\u09bf\u0993 \u09a8\u09be? \u09a4\u09be\u09b9\u09b2\u09c7 \u09a6\u09be\u0981\u09dc\u09bf\u09df\u09c7 \u09a5\u09c7\u0995\u09cb \u09a8\u09be\u0964 \u09ad\u09bf\u09dc\u09c7\u09b0 \u09ae\u09be\u099d\u09c7 \u09b9\u09be\u09b0\u09bf\u09df\u09c7 \u09af\u09c7\u0993 \u09a8\u09be\u0964 \u09a8\u09bf\u099c\u09c7\u09b0 \u0997\u09b2\u09cd\u09aa\u099f\u09be \u09a8\u09bf\u099c\u09c7\u0987 \u09b2\u09bf\u0996\u09cb\u0964 \u0986\u099c\u0987 \u09af\u09c1\u0995\u09cd\u09a4 \u09b9\u0993 #ZeroOlympiad \u098f\u0964",
    "link": "https://www.facebook.com/FaatihaAayatOfficial/posts/pfbid07o8SpTNKt8UWiGMn37XUxhAhEUg2xXJa1eP62hhn663s6R4ngJDHerX1JbXLtBSrl",
    "guid": "https://www.facebook.com/FaatihaAayatOfficial/posts/pfbid07o8SpTNKt8UWiGMn37XUxhAhEUg2xXJa1eP62hhn663s6R4ngJDHerX1JbXLtBSrl",
    "pubDate": "2026-04-20T12:07:34.914416+00:00",
    "image": "https://scontent-dfw6-1.xx.fbcdn.net/v/t39.30808-6/672681391_1982003839106688_6802611648595666321_n.jpg?stp=cp6_dst-jpg_p526x296_tt6&_nc_cat=101&ccb=1-7&_nc_sid=7b2446&_nc_ohc=D1wx_m7s8dEQ7kNvwEyiZl2&_nc_oc=AdowMAiTUfg3nAL4SYpXMLMf2pxpApnZrC50wenz91V37eHCufk90qJjsuJo71asQfg&_nc_zt=23&_nc_ht=scontent-dfw6-1.xx&_nc_gid=KkpW2ztOW1KD1saucgp6tQ&_nc_ss=7a389&oh=00_Af026G6FKgmzxzXcT1TYSCvtawfqw5ZasI3gjwLKnFTbMQ&oe=69ED4236"
  },
  {
    "title": "\u09b2\u09bf\u099f\u09a8 \u0986\u0982\u0995\u09c7\u09b2\u09c7\u09b0 \u09b9\u09be\u09a4\u09c7 \u09ad\u09b0 \u0995\u09b0\u09c7 \u09af\u09c7\u09a8 \u098f\u0995\u099d\u09be\u0981\u0995 \u09b8\u09cd\u09ac\u09aa\u09cd\u09a8 \u098f\u09b8\u09c7 \u09aa\u09cc\u0981\u099b\u09c7\u099b\u09c7\u0964 #GLTS-\u098f\u09b0 \u09b8\u09a6\u09cd\u09af \u09aa\u09cd\u09b0\u0995\u09be\u09b6\u09bf\u09a4 \u09ac...",
    "description": "\u09b2\u09bf\u099f\u09a8 \u0986\u0982\u0995\u09c7\u09b2\u09c7\u09b0 \u09b9\u09be\u09a4\u09c7 \u09ad\u09b0 \u0995\u09b0\u09c7 \u09af\u09c7\u09a8 \u098f\u0995\u099d\u09be\u0981\u0995 \u09b8\u09cd\u09ac\u09aa\u09cd\u09a8 \u098f\u09b8\u09c7 \u09aa\u09cc\u0981\u099b\u09c7\u099b\u09c7\u0964 #GLTS-\u098f\u09b0 \u09b8\u09a6\u09cd\u09af \u09aa\u09cd\u09b0\u0995\u09be\u09b6\u09bf\u09a4 \u09ac\u0987\u0997\u09c1\u09b2\u09cb\u0964 \u0986\u09ae\u09bf \u09b6\u09c1\u09a7\u09c1 \u09ac\u0987\u0997\u09c1\u09b2\u09cb \u09ac\u09c1\u099d\u09c7 \u09a8\u09bf\u099a\u09cd\u099b\u09bf \u09a8\u09be\u0964 \u09b6\u09c1\u09a8\u09c7 \u09a8\u09bf\u099a\u09cd\u099b\u09bf \u09b2\u09bf\u099f\u09a8 \u0986\u0982\u0995\u09c7\u09b2\u09c7\u09b0 \u09ae\u09a4 \u09ae\u09be\u09a8\u09c1\u09b7\u09a6\u09c7\u09b0 \u09a8\u09c0\u09b0\u09ac \u0995\u09a3\u09cd\u09a0, \u0985\u09a8\u09c1\u09ad\u09ac \u0995\u09b0\u099b\u09bf \u09a4\u09be\u09a6\u09c7\u09b0 \u09ad\u09c7\u09a4\u09b0\u09c7 \u09b2\u09c1\u0995\u09bf\u09df\u09c7 \u09a5\u09be\u0995\u09be \u09b8\u09cd\u09ac\u09aa\u09cd\u09a8 \u0986\u09b0 \u09aa\u09b0\u09bf\u09ac\u09b0\u09cd\u09a4\u09a8\u09c7\u09b0 \u0986\u09b9\u09cd\u09ac\u09be\u09a8\u0964 \u09b2\u09bf\u099f\u09a8 \u0986\u0982\u0995\u09c7\u09b2\u09c7\u09b0 \u099a\u09cb\u0996\u09c7 \u09ae\u09c1\u0996\u09c7 \u09af\u09c7 \u0986\u09a8\u09cd\u09a4\u09b0\u09bf\u0995\u09a4\u09be, \u09a4\u09be \u09af\u09c7\u09a8 \u09ac\u09b2\u09c7 \u09a6\u09bf\u099a\u09cd\u099b\u09c7 \u098f\u0987 \u09ac\u0987\u0997\u09c1\u09b2\u09cb \u0995\u09c7\u09ac\u09b2 \u0995\u09be\u0997\u099c\u09c7\u09b0 \u09a8\u09df, \u098f\u0997\u09c1\u09b2\u09cb \u09ad\u09ac\u09bf\u09b7\u09cd\u09af\u09ce \u0997\u09dc\u09be\u09b0 \u09b9\u09be\u09a4\u09bf\u09df\u09be\u09b0\u0964 \u098f\u0987 \u09ae\u09c1\u09b9\u09c2\u09b0\u09cd\u09a4\u099f\u09be \u09a4\u09be\u0987 \u09b6\u09c1\u09a7\u09c1 \u09ac\u0987 \u0997\u09cd\u09b0\u09b9\u09a3\u09c7\u09b0 \u09a8\u09df\u0964 \u098f\u099f\u09be \u098f\u0995 \u09a8\u09a4\u09c1\u09a8 \u09af\u09be\u09a4\u09cd\u09b0\u09be\u09b0 \u09b6\u09c1\u09b0\u09c1, \u09af\u09c7\u0996\u09be\u09a8\u09c7 \u09aa\u09cd\u09b0\u09a4\u09bf\u099f\u09bf \u09aa\u09c3\u09b7\u09cd\u09a0\u09be \u0996\u09c1\u09b2\u09ac\u09c7 \u098f\u0995\u09c7\u0995\u099f\u09bf \u0986\u09b2\u09cb\u09b0 \u09a6\u09b0\u099c\u09be\u0964",
    "link": "https://www.facebook.com/FaatihaAayatOfficial/videos/2197331821024272/",
    "guid": "https://www.facebook.com/FaatihaAayatOfficial/videos/2197331821024272/",
    "pubDate": "2026-04-20T12:07:36.956462+00:00",
    "image": "https://scontent-dfw6-1.xx.fbcdn.net/v/t15.5256-10/675982518_1654443329232240_2090464021637408769_n.jpg?stp=dst-jpg_s960x960_tt6&_nc_cat=106&ccb=1-7&_nc_sid=b86bae&_nc_ohc=dR0Fvyzu2qgQ7kNvwH4kaP7&_nc_oc=AdrVpltfh6Py3CQ9nfOPzWYgpEy4lKfVRyJJBtPm-JDYWUjcdy-v0hy-bBdqy5Guvj0&_nc_zt=23&_nc_ht=scontent-dfw6-1.xx&_nc_gid=KkpW2ztOW1KD1saucgp6tQ&_nc_ss=7a389&oh=00_Af2KdAvl-Pl1Q0fAqRhfxvG2zYgs97wdXS1ULxv-omItCw&oe=69ED3312"
  },
  {
    "title": "#ZeroOlympiad \u098f\u09b0 \u09aa\u09c1\u09b0\u09b7\u09cd\u0995\u09be\u09b0\u09c7\u09b0 \u09a4\u09be\u09b2\u09bf\u0995\u09be\u09a4\u09cb \u0986\u0997\u09c7\u0987 \u09a6\u09c7\u0996\u09c7\u099b\u09c7\u09a8\u0964 \u0995\u09bf\u09a8\u09cd\u09a4\u09c1 \u098f\u0997\u09c1\u09b2\u09cb \u0986\u09aa\u09a8\u09be\u0995\u09c7 \u0995\u09bf\u09ad\u09be\u09ac\u09c7 \u09ac\u09c7...",
    "description": "#ZeroOlympiad \u098f\u09b0 \u09aa\u09c1\u09b0\u09b7\u09cd\u0995\u09be\u09b0\u09c7\u09b0 \u09a4\u09be\u09b2\u09bf\u0995\u09be\u09a4\u09cb \u0986\u0997\u09c7\u0987 \u09a6\u09c7\u0996\u09c7\u099b\u09c7\u09a8\u0964 \u0995\u09bf\u09a8\u09cd\u09a4\u09c1 \u098f\u0997\u09c1\u09b2\u09cb \u0986\u09aa\u09a8\u09be\u0995\u09c7 \u0995\u09bf\u09ad\u09be\u09ac\u09c7 \u09ac\u09c7\u09a8\u09bf\u09ab\u09bf\u099f\u09c7\u09a1 \u0995\u09b0\u09ac\u09c7? \u0985\u09b0\u09cd\u09a5\u09be\u09ce, \u0986\u09aa\u09a8\u09be\u09b0 \u09b2\u09be\u09ad \u0995\u09c0? \u2014 United Nations \u098f\u09b0 \u0995\u09cb\u09b0\u09cd\u09b8 \u09b8\u09ae\u09cd\u09aa\u09a8\u09cd\u09a8 \u0995\u09b0\u09b2\u09c7 \u09a4\u09be\u09a6\u09c7\u09b0 \u09a5\u09c7\u0995\u09c7 \u09af\u09c7 \u09b8\u09be\u09b0\u09cd\u099f\u09bf\u09ab\u09bf\u0995\u09c7\u099f \u09aa\u09be\u0993\u09df\u09be \u09af\u09be\u09ac\u09c7 \u0986\u09b0 Zero Olympiad \u098f\u09b0 \u09e7\u09ae \u09b0\u09be\u0989\u09a8\u09cd\u09a1\u09c7\u09b0 \u09aa\u09b0\u09c0\u0995\u09cd\u09b7\u09be \u09a6\u09c7\u09df\u09be\u09b0 \u09aa\u09b0 Commonwealth \u09a5\u09c7\u0995\u09c7 \u09af\u09c7 \u09b8\u09be\u09b0\u09cd\u099f\u09bf\u09ab\u09bf\u0995\u09c7\u099f \u09aa\u09be\u0993\u09df\u09be \u09af\u09be\u09ac\u09c7 \u09a4\u09be Strong ECA \u09ac\u09be #ExtraCurricularActivities \u09b9\u09bf\u09b8\u09c7\u09ac\u09c7 \u09aa\u09b0\u09ac\u09b0\u09cd\u09a4\u09c0\u09a4\u09c7 \u0989\u099a\u09cd\u099a\u09b6\u09bf\u0995\u09cd\u09b7\u09be \u0993 \u0995\u09b0\u09cd\u09ae\u0995\u09cd\u09b7\u09c7\u09a4\u09cd\u09b0\u09c7 \u09b8\u09c1\u09a6\u09c3\u09dd \u09ad\u09c2\u09ae\u09bf\u0995\u09be \u09b0\u09be\u0996\u09ac\u09c7\u0964 \u09af\u09c1\u0995\u09cd\u09a4\u09b0\u09be\u09b7\u09cd\u099f\u09cd\u09b0\u09c7\u09b0 Washington University of Science and Technology \u098f\u09b0 \u09b8\u09cd\u0995\u09b2\u09be\u09b0\u09b6\u09bf\u09aa \u0986\u09b0 \u0985\u09b8\u09cd\u099f\u09cd\u09b0\u09c7\u09b2\u09bf\u09df\u09be\u09b0 Murdoch University \u098f\u09b0 \u0995\u09cb\u09b2\u09be\u09ac\u09cb\u09b0\u09c7\u09b6\u09a8 \u0986\u09aa\u09a8\u09be\u09b0 #OverseasEducation \u0986\u09b0\u09cb \u09b8\u09b9\u099c \u0995\u09b0\u09ac\u09c7\u0964 \u09ae\u09be\u09b2\u09df\u09c7\u09b6\u09bf\u09df\u09be\u09b0 Asia Pacific University of Technology & Innovation \u098f \u09e7\u09e6-\u09e7\u09e8 \u099c\u09c1\u09b2\u09be\u0987 \u0986\u09df\u09cb\u099c\u09bf\u09a4 #LeadershipBootcamp \u0986\u09aa\u09a8\u09be\u0995\u09c7 \u0995\u09b0\u09c7 \u09a4\u09c1\u09b2\u09ac\u09c7 \u09b8\u09a4\u200d\u09cd\u09af\u09bf\u0995\u09be\u09b0\u09c7\u09b0 #GlobalLeader\u0964 \u098f\u09b0\u0995\u09ae\u0987 \u09aa\u09b0\u09ac\u09b0\u09cd\u09a4\u09c0 #InternationalTrip \u098f \u0986\u09aa\u09a8\u09be\u09a6\u09c7\u09b0 #China \u09a8\u09bf\u09df\u09c7 \u09af\u09be\u09ac\u09c7 Scholarship Helpline \u09a8\u09be\u09ae\u09c7\u09b0 \u09a6\u09c7\u09b6\u09b8\u09c7\u09b0\u09be #StudyAbroad \u09aa\u09cd\u09b0\u09a4\u09bf\u09b7\u09cd\u09a0\u09be\u09a8\u0964 Sanrin Gakkou \u098f\u09b0 \u099c\u09be\u09aa\u09be\u09a8\u09bf\u099c \u0995\u09cb\u09b0\u09cd\u09b8 \u0986\u09aa\u09a8\u09be\u09b0 \u09a6\u0995\u09cd\u09b7\u09a4\u09be \u09ac\u09be\u09dc\u09be\u09ac\u09c7 \u0986\u09b0\u09c7\u0995\u099f\u09be \u0986\u09a8\u09cd\u09a4\u09be\u09b0\u09cd\u099c\u09be\u09a4\u09bf\u0995 \u09ad\u09be\u09b7\u09be\u09df\u0964 \u09af\u09c7 \u09e8\u09ea\u099f\u09be \u09ab\u09cd\u09b0\u09bf \u0995\u09cd\u09b2\u09be\u09b6 \u0995\u09b0\u09be\u09ac\u09c7 MFH Science Club, \u09b8\u09c7\u0996\u09be\u09a8 \u09a5\u09c7\u0995\u09c7 \u09a8\u09bf\u09a4\u09c7 \u09aa\u09be\u09b0\u09ac\u09c7\u09a8 \u0986\u09a8\u09cd\u09a4\u09b0\u09cd\u099c\u09be\u09a4\u09bf\u0995 \u0997\u09a8\u09bf\u09a4 \u0985\u09b2\u09bf\u09ae\u09cd\u09aa\u09bf\u09df\u09be\u09a1\u09c7\u09b0 \u099c\u09a8\u200d\u09cd\u09af \u09b8\u09c7\u09b0\u09be \u09aa\u09cd\u09b0\u09b8\u09cd\u09a4\u09c1\u09a4\u09bf\u0964 #EnglishWoldCup \u098f\u09b0 \u09b8\u09bf\u09b2\u09c7\u0995\u09b6\u09a8 \u09b0\u09be\u0989\u09a8\u09cd\u09a1\u09c7 \u09ab\u09cd\u09b0\u09bf \u0985\u0982\u09b6 \u09a8\u09bf\u09df\u09c7 #Bangladesh \u0995\u09c7 \u09b0\u09bf\u09aa\u09cd\u09b0\u09c7\u099c\u09c7\u09a8\u09cd\u099f \u0995\u09b0\u09ac\u09c7\u09a8 International Olympiads \u098f\u0964 Creative IT Institute \u098f\u09b0 \u0995\u09be\u09b8\u09cd\u099f\u09ae\u09be\u0987\u099c\u09a1 \u0986\u0987\u099f\u09bf \u0995\u09cb\u09b0\u09cd\u09b8 \u0986\u09b0 10 Minute School \u098f\u09b0 \u09aa\u09cd\u09b0\u09ab\u09c7\u09b6\u09a8\u09be\u09b2 \u09b2\u200d\u09cd\u09af\u09be\u0982\u0997\u09c1\u09df\u09c7\u099c \u0995\u09cb\u09b0\u09cd\u09b8 \u09ac\u09bf\u099c\u09df\u09c0\u09a6\u09c7\u09b0 \u0995\u09b0\u09ac\u09c7 \u0986\u09b0\u09cb \u09b6\u09be\u09a8\u09bf\u09a4\u0964 \u098f\u0996\u09a8 \u09b8\u09bf\u09a6\u09cd\u09a7\u09be\u09a8\u09cd\u09a4 \u0986\u09aa\u09a8\u09be\u09b0\u0964",
    "link": "https://www.facebook.com/FaatihaAayatOfficial/videos/26370565662627320/",
    "guid": "https://www.facebook.com/FaatihaAayatOfficial/videos/26370565662627320/",
    "pubDate": "2026-04-20T12:07:39.033699+00:00",
    "image": "https://scontent-dfw6-1.xx.fbcdn.net/v/t15.5256-10/675272682_1628980574982768_7625878187898052809_n.jpg?stp=dst-jpg_s960x960_tt6&_nc_cat=103&ccb=1-7&_nc_sid=b86bae&_nc_ohc=XRehZ4JUla0Q7kNvwH02aCM&_nc_oc=Ado4suu5zENEbsfV8WtRl92-oXSUFz5ds2JCWeSdK2nje_6SrAgysq7iPrTyVtDdjHE&_nc_zt=23&_nc_ht=scontent-dfw6-1.xx&_nc_gid=KkpW2ztOW1KD1saucgp6tQ&_nc_ss=7a389&oh=00_Af1gVhB_PMPB1CfurWzIlZ_HajkB0P43uNX-DoLZwlifSQ&oe=69ED20E6"
  }
]