[
  {
    "title": "\u099b\u09ac\u09bf: \u09b0\u0998\u09c1 \u09b0\u09be\u0987 \u09ab\u09be\u0989\u09a8\u09cd\u09a1\u09c7\u09b6\u09a8 \u0985\u09ab\u09bf\u09b6\u09bf\u09df\u09be\u09b2 \u0986\u09b0\u09cd\u0995\u09be\u0987\u09ad\u09b8\u0964 \u09e9\u09eb \u09ae\u09bf.\u09ae\u09bf \u098f\u09b8\u098f\u09b2\u0986\u09b0 \u0995\u09cd\u09af\u09be\u09ae\u09c7\u09b0\u09be\u09df \u09a4\u09cb\u09b2\u09be\u0964 \u09b8\u09c7-\u09b8\u09ae\u09df...",
    "description": "\u099b\u09ac\u09bf: \u09b0\u0998\u09c1 \u09b0\u09be\u0987 \u09ab\u09be\u0989\u09a8\u09cd\u09a1\u09c7\u09b6\u09a8 \u0985\u09ab\u09bf\u09b6\u09bf\u09df\u09be\u09b2 \u0986\u09b0\u09cd\u0995\u09be\u0987\u09ad\u09b8\u0964 \u09e9\u09eb \u09ae\u09bf.\u09ae\u09bf \u098f\u09b8\u098f\u09b2\u0986\u09b0 \u0995\u09cd\u09af\u09be\u09ae\u09c7\u09b0\u09be\u09df \u09a4\u09cb\u09b2\u09be\u0964 \u09b8\u09c7-\u09b8\u09ae\u09df\u09c7 \u0995\u09cd\u09af\u09be\u09a8\u09a8 F1 35mm SLR \u0995\u09cd\u09af\u09be\u09ae\u09c7\u09b0\u09be \u09ab\u099f\u09cb\u09b8\u09be\u0982\u09ac\u09be\u09a6\u09bf\u0995\u09a6\u09c7\u09b0 \u0995\u09be\u099b\u09c7 \u099c\u09a8\u09aa\u09cd\u09b0\u09bf\u09df \u099b\u09bf\u09b2\u09cb\u0964 \u09ab\u099f\u09cb\u0995\u09be\u09b0\u09cd\u09a1 \u0995\u09be\u09b0\u09cd\u099f\u09c7\u09b8\u09bf: \u09ae\u09b9\u09bf\u0989\u09a6\u09cd\u09a6\u09bf\u09a8 \u09ae\u09cb\u09b9\u09be\u09ae\u09cd\u09ae\u09a6 \u09ad\u09b2\u09be\u09a8\u09cd\u099f\u09bf\u09df\u09be\u09b0\u09cd\u09b8 \u099f\u09bf\u09ae\u0964",
    "link": "https://www.facebook.com/oiraboti.book/posts/pfbid02iqHSUNCPB92FGhFu4HQH57KvQ9Sh87mVcgH4Lv2L7fheuFJ6yM1v4AwxKLTfJkF9l",
    "guid": "https://www.facebook.com/oiraboti.book/posts/pfbid02iqHSUNCPB92FGhFu4HQH57KvQ9Sh87mVcgH4Lv2L7fheuFJ6yM1v4AwxKLTfJkF9l",
    "pubDate": "2026-03-06T02:43:53.842465+00:00",
    "image": "https://scontent-sin6-1.xx.fbcdn.net/v/t39.30808-6/646846234_931185536539350_3954061302367839907_n.jpg?stp=dst-jpg_p526x296_tt6&_nc_cat=111&ccb=1-7&_nc_sid=13d280&_nc_ohc=lFFzK7J2Al0Q7kNvwEe4Gde&_nc_oc=AdmmUM4rB4oM8Ul3KojOqkPCirBpx2iMUdxEz-si5NLhc01IhLY1wsCrqnHzahbsMok&_nc_zt=23&_nc_ht=scontent-sin6-1.xx&_nc_gid=birMIeovW74Nq0l3RJWxag&_nc_ss=8&oh=00_AfywvfRzvEevUED17DBiYY4WG6EFi9vVkkjyQmHFO-63qA&oe=69B03183"
  },
  {
    "title": "\u09ac\u0987\u09ae\u09c7\u09b2\u09be \u09a5\u09c7\u0995\u09c7 \u0995\u09bf\u09a8\u09c1\u09a8 \u09ed\u09eb% \u09ae\u09c2\u09b2\u09cd\u09af\u09c7\u0964",
    "description": "\u09ac\u0987\u09ae\u09c7\u09b2\u09be \u09a5\u09c7\u0995\u09c7 \u0995\u09bf\u09a8\u09c1\u09a8 \u09ed\u09eb% \u09ae\u09c2\u09b2\u09cd\u09af\u09c7\u0964",
    "link": "https://www.facebook.com/oiraboti.book/posts/pfbid027Sa3qnZPhmPwqrAQiXFTXWnvYieeGJwUstd7DtpPBXvx1xVnN6Xj4wGuJcztjocwl",
    "guid": "https://www.facebook.com/oiraboti.book/posts/pfbid027Sa3qnZPhmPwqrAQiXFTXWnvYieeGJwUstd7DtpPBXvx1xVnN6Xj4wGuJcztjocwl",
    "pubDate": "2026-03-05T15:29:55.884857+00:00",
    "image": "https://scontent-sin6-3.xx.fbcdn.net/v/t39.30808-6/647514588_930832366574667_4620009872439996063_n.jpg?stp=dst-jpg_s600x600_tt6&_nc_cat=110&ccb=1-7&_nc_sid=13d280&_nc_ohc=TABz3hsoAXkQ7kNvwGMhFju&_nc_oc=AdmH-8GjpvInjjy3N7KF0CvmwIXoKLPNEaq9gAdSLdmijU5cNLhNV5ml9OTP7yemSz8&_nc_zt=23&_nc_ht=scontent-sin6-3.xx&_nc_gid=ucYwUSSNznC2lJSQKgRBig&_nc_ss=8&oh=00_AfzXdqcUzpT7i7d9FmgEg67u2BtN3NlTFRn_pEGzsPk5eA&oe=69B00D78"
  },
  {
    "title": "\u09ab\u099f\u09cb \u0995\u09be\u09b0\u09cd\u099f\u09c7\u09b8\u09bf: \u09b0\u0998\u09c1 \u09b0\u09be\u09df \u09ab\u09be\u0989\u09a8\u09cd\u09a1\u09c7\u09b6\u09a8",
    "description": "\u09ab\u099f\u09cb \u0995\u09be\u09b0\u09cd\u099f\u09c7\u09b8\u09bf: \u09b0\u0998\u09c1 \u09b0\u09be\u09df \u09ab\u09be\u0989\u09a8\u09cd\u09a1\u09c7\u09b6\u09a8",
    "link": "https://www.facebook.com/oiraboti.book/posts/pfbid0cWtHCQKa64VovJvZaTU4ZLXn1KoiZC3NP5mBC8VmapLvEkcNQuG8en1a1FfVg5Hvl",
    "guid": "https://www.facebook.com/oiraboti.book/posts/pfbid0cWtHCQKa64VovJvZaTU4ZLXn1KoiZC3NP5mBC8VmapLvEkcNQuG8en1a1FfVg5Hvl",
    "pubDate": "2026-03-05T14:29:57.928673+00:00",
    "image": "https://scontent-sin11-1.xx.fbcdn.net/v/t39.30808-6/648318189_930791063245464_7724970246730985924_n.jpg?stp=dst-jpg_p526x296_tt6&_nc_cat=1&ccb=1-7&_nc_sid=13d280&_nc_ohc=EPKbQWk1eWAQ7kNvwEpvXF6&_nc_oc=AdllLrmytO4It5rqlLC5fCp8ESVPAwqKh1VELn48AkPk9eHsuhbBkdXD-2akuleMGLM&_nc_zt=23&_nc_ht=scontent-sin11-1.xx&_nc_gid=ucYwUSSNznC2lJSQKgRBig&_nc_ss=8&oh=00_AfwDnS3zFXScz3vCIOASCWJwrAHJni6aT7DsXRYpQjicMQ&oe=69B03021"
  },
  {
    "title": "\u09ac\u0987\u09ae\u09c7\u09b2\u09be\u09df \u09b8\u09ac\u099a\u09c7\u09df\u09c7 \u09ac\u09c7\u09b6\u09bf \u09ac\u09bf\u0995\u09cd\u09b0\u09bf \u09b9\u099a\u09cd\u099b\u09c7 \u09ae\u09b9\u09bf\u0989\u09a6\u09cd\u09a6\u09bf\u09a8 \u09ae\u09cb\u09b9\u09be\u09ae\u09cd\u09ae\u09a6\u09c7\u09b0 \u09ac\u0987\u0964 \u09aa\u09cd\u09b0\u0995\u09be\u09b6\u09bf\u09a4 \u09ec\u099f\u09bf \u09ac\u0987\u09df\u09c7\u09b0 \u09ec\u099f\u09bf...",
    "description": "\u09ac\u0987\u09ae\u09c7\u09b2\u09be\u09df \u09b8\u09ac\u099a\u09c7\u09df\u09c7 \u09ac\u09c7\u09b6\u09bf \u09ac\u09bf\u0995\u09cd\u09b0\u09bf \u09b9\u099a\u09cd\u099b\u09c7 \u09ae\u09b9\u09bf\u0989\u09a6\u09cd\u09a6\u09bf\u09a8 \u09ae\u09cb\u09b9\u09be\u09ae\u09cd\u09ae\u09a6\u09c7\u09b0 \u09ac\u0987\u0964 \u09aa\u09cd\u09b0\u0995\u09be\u09b6\u09bf\u09a4 \u09ec\u099f\u09bf \u09ac\u0987\u09df\u09c7\u09b0 \u09ec\u099f\u09bf\u0987 \u0997\u09a3\u09b9\u09be\u09b0\u09c7 \u09b8\u09be\u09b0\u09be \u09ac\u099b\u09b0 \u09a7\u09b0\u09c7 \u09ac\u09bf\u0995\u09cd\u09b0\u09bf \u09b9\u099a\u09cd\u099b\u09c7\u0964 \u099b\u09dc\u09bf\u09df\u09c7 \u09aa\u09dc\u099b\u09c7 \u09b8\u09be\u09b0\u09be \u09a6\u09c7\u09b6\u09c7\u0964 \u09b8\u09ac \u09b6\u09cd\u09b0\u09c7\u09a3\u09c0 \u09aa\u09c7\u09b6\u09be\u09b0 \u09aa\u09be\u09a0\u0995\u09c7\u09b0 \u09ae\u09be\u099d\u09c7\u0964 (\u098f\u09a1\u09ae\u09bf\u09a8)",
    "link": "https://www.facebook.com/oiraboti.book/posts/pfbid02LXueUwENf2XpEVX4ePJ277QX6Wr5PgRBWYagdcq1a8ue3K6T8g5kyYi3jGGKT3Pcl",
    "guid": "https://www.facebook.com/oiraboti.book/posts/pfbid02LXueUwENf2XpEVX4ePJ277QX6Wr5PgRBWYagdcq1a8ue3K6T8g5kyYi3jGGKT3Pcl",
    "pubDate": "2026-03-05T06:29:59.977881+00:00",
    "image": "https://scontent-sin2-3.xx.fbcdn.net/v/t39.30808-6/645363683_930519829939254_5058257348146187062_n.jpg?stp=dst-jpg_p526x296_tt6&_nc_cat=107&ccb=1-7&_nc_sid=7b2446&_nc_ohc=t-RYweaCPzoQ7kNvwE_FQRO&_nc_oc=Admmnh2JzQLgnu7GmsbzLIUeXzMu8Pg3jW38SAP3IPqGutP_VkiA3mZiRAJ2JXwgsHo&_nc_zt=23&_nc_ht=scontent-sin2-3.xx&_nc_gid=ucYwUSSNznC2lJSQKgRBig&_nc_ss=8&oh=00_AfzmXCDBDFZzpLAIySPQSLOJXW-Kr-fynhyDRMLz6Kdllw&oe=69B027E4"
  },
  {
    "title": "\u0995\u09be\u09b0\u09cd\u099f\u09c7\u09b8\u09bf: \u09b0\u0998\u09c1 \u09b0\u09be\u09df \u09ab\u09be\u0989\u09a8\u09cd\u09a1\u09c7\u09b6\u09a8",
    "description": "\u0995\u09be\u09b0\u09cd\u099f\u09c7\u09b8\u09bf: \u09b0\u0998\u09c1 \u09b0\u09be\u09df \u09ab\u09be\u0989\u09a8\u09cd\u09a1\u09c7\u09b6\u09a8",
    "link": "https://www.facebook.com/oiraboti.book/posts/pfbid02efGrk24i4uV9BnXxR2XhpcAmsoQkGaQhTgwuRS8ztJ1oeJvJsYrKA8soq8VEWGiRl",
    "guid": "https://www.facebook.com/oiraboti.book/posts/pfbid02efGrk24i4uV9BnXxR2XhpcAmsoQkGaQhTgwuRS8ztJ1oeJvJsYrKA8soq8VEWGiRl",
    "pubDate": "2026-03-05T04:30:02.020899+00:00",
    "image": "https://scontent-sin2-2.xx.fbcdn.net/v/t39.30808-6/646794339_930466026611301_3444547537415813288_n.jpg?stp=dst-jpg_p526x296_tt6&_nc_cat=103&ccb=1-7&_nc_sid=13d280&_nc_ohc=o8JuKTYDUj8Q7kNvwHM1wlv&_nc_oc=Admn0v8rrdCAbovTODa2u40slIBhLQpNbYAOMMWfDmN7h0FCqMbm21CV7xdJKFH-M4I&_nc_zt=23&_nc_ht=scontent-sin2-2.xx&_nc_gid=izuIFnC-IFAe9FhWwo1QHw&_nc_ss=8&oh=00_AfzsXi4jE2VmHTr_-jSGlxc4-5hMCqpyY7sPASX2HD8D6A&oe=69B01E86"
  }
]