[
  {
    "title": "Bhai ami expose video bhabsilam",
    "description": "Bhai ami expose video bhabsilam",
    "link": "https://www.facebook.com/therealsalmanmuqtadir/posts/pfbid0TKHpLhHFfp96Sh3kuvjDZAvmr4kCHFa8b1WYdoCshGsQ6njcPnvqz8soUZdWF1GGl",
    "guid": "https://www.facebook.com/therealsalmanmuqtadir/posts/pfbid0TKHpLhHFfp96Sh3kuvjDZAvmr4kCHFa8b1WYdoCshGsQ6njcPnvqz8soUZdWF1GGl",
    "pubDate": "2026-03-16T17:31:26.215953+00:00",
    "image": null
  },
  {
    "title": "EID OUTFIT Drive Boosted",
    "description": "EID OUTFIT Drive Boosted",
    "link": "https://www.facebook.com/therealsalmanmuqtadir/posts/pfbid0fBKC1W7QPxoCLtBiNTybdLdmtrABdHNvQHCVSaXXj6h6MqxHxXLdpHFafcb5C8c1l",
    "guid": "https://www.facebook.com/therealsalmanmuqtadir/posts/pfbid0fBKC1W7QPxoCLtBiNTybdLdmtrABdHNvQHCVSaXXj6h6MqxHxXLdpHFafcb5C8c1l",
    "pubDate": "2026-03-16T11:31:28.279089+00:00",
    "image": "https://scontent-sjc6-1.xx.fbcdn.net/v/t39.30808-6/653582414_1469083027908463_3260250927401246086_n.jpg?stp=dst-jpg_s590x590_tt6&_nc_cat=1&ccb=1-7&_nc_sid=7b2446&_nc_ohc=22zlFfks9xcQ7kNvwEWTbLb&_nc_oc=AdnfmjkCqxBuDrfO2j6kHetYGyIrd2wVQrPhajnhv2-pBy9qwiNojc81BC2tzseTIB0&_nc_zt=23&_nc_ht=scontent-sjc6-1.xx&_nc_gid=vDthGcO6WOg0XcoB9g4eDw&_nc_ss=8&oh=00_AfyMItH9OMjVSBd4QsoAr2aLMxT7rz3jnhNqH-8c_yJvrQ&oe=69BE8ED9"
  },
  {
    "title": "Bank account : Mirror :",
    "description": "Bank account : Mirror :",
    "link": "https://www.facebook.com/therealsalmanmuqtadir",
    "guid": "https://www.facebook.com/therealsalmanmuqtadir#6_1773718290",
    "pubDate": "2026-03-15T03:31:30.384665+00:00",
    "image": "https://scontent-sjc3-1.xx.fbcdn.net/v/t15.5256-10/648100137_1828685567849453_4390551561392029990_n.jpg?stp=dst-jpg_s960x960_tt6&_nc_cat=106&ccb=1-7&_nc_sid=d2b52d&_nc_ohc=L9eagOEypxMQ7kNvwHQD_57&_nc_oc=Adm9B4dhHQdHw7CGGhSPqeYN41M4672QuUcaxPi-HdwNOuVvI2H3QoHrpYJfdRZND5Y&_nc_zt=23&_nc_ht=scontent-sjc3-1.xx&_nc_gid=vDthGcO6WOg0XcoB9g4eDw&_nc_ss=8&oh=00_AfxULKdJWKz-WQkfmTDnqh0TFoJN-IdD2o-oXNbUgv_yvg&oe=69BE981E"
  },
  {
    "title": "Salman Mohammad Muqtadir \u00b7 \ufeffObhodro Prem \u00b7 Salman Muqtadir \u00b7 0:00 / 0:15",
    "description": "Salman Mohammad Muqtadir \u00b7 \ufeffObhodro Prem \u00b7 Salman Muqtadir \u00b7 0:00 / 0:15",
    "link": "https://www.facebook.com/therealsalmanmuqtadir",
    "guid": "https://www.facebook.com/therealsalmanmuqtadir#9_1773718292",
    "pubDate": "2026-03-14T03:31:32.455670+00:00",
    "image": "https://scontent-sjc3-1.xx.fbcdn.net/v/t15.5256-10/650291479_1427061565386681_5623271863787171424_n.jpg?stp=dst-jpg_s960x960_tt6&_nc_cat=106&ccb=1-7&_nc_sid=d2b52d&_nc_ohc=96E3aJseXT8Q7kNvwGRvpNO&_nc_oc=AdkICnPtAhtSoENs1oKAI4K4dPlXoNsh0EKVaD6f2j92YKqeleqAoKHONj_6PvQyfV0&_nc_zt=23&_nc_ht=scontent-sjc3-1.xx&_nc_gid=vDthGcO6WOg0XcoB9g4eDw&_nc_ss=8&oh=00_AfxRlljPwH77AxIaxce2TpBiR-yuxbbSNE1kf6_YO8MIMw&oe=69BEB16C"
  },
  {
    "title": "How we allow real harassment and molestation cases to go free in bangladesh thro...",
    "description": "How we allow real harassment and molestation cases to go free in bangladesh through our lack of understanding.",
    "link": "https://www.facebook.com/therealsalmanmuqtadir",
    "guid": "https://www.facebook.com/therealsalmanmuqtadir#11_1773718294",
    "pubDate": "2026-03-12T03:31:34.526134+00:00",
    "image": "https://scontent-sjc3-1.xx.fbcdn.net/v/t15.5256-10/650300376_906211622392254_8094307538759704834_n.jpg?stp=dst-jpg_s960x960_tt6&_nc_cat=105&ccb=1-7&_nc_sid=5fad0e&_nc_ohc=1N8hLBpYc0oQ7kNvwHkpwDg&_nc_oc=AdmTJON0OUVDa2m5WujVQ6nC40Q7-EcCDoZwF17-1wZ5mHLw7_mC-VecrhCuX4ELkZk&_nc_zt=23&_nc_ht=scontent-sjc3-1.xx&_nc_gid=ELxMdyVXWpfKRTqGZ7bIAA&_nc_ss=8&oh=00_Afx-zZJFui4UhtB1mvvNg3w2MI2GEDSmTcvP1OK8MnRHvw&oe=69BE9174"
  }
]